shivyc/__init__.py
shivyc/asm_cmds.py
shivyc/asm_gen.py
shivyc/ctypes.py
shivyc/errors.py
shivyc/il_gen.py
shivyc/lexer.py
shivyc/main.py
shivyc/preproc.py
shivyc/spots.py
shivyc/token_kinds.py
shivyc/tokens.py
shivyc/il_cmds/__init__.py
shivyc/il_cmds/base.py
shivyc/il_cmds/compare.py
shivyc/il_cmds/control.py
shivyc/il_cmds/math.py
shivyc/il_cmds/value.py
shivyc/include/ctype.h
shivyc/include/stdbool.h
shivyc/include/stdio.h
shivyc/include/stdlib.h
shivyc/include/string.h
shivyc/parser/__init__.py
shivyc/parser/declaration.py
shivyc/parser/expression.py
shivyc/parser/parser.py
shivyc/parser/statement.py
shivyc/parser/utils.py
shivyc/tree/__init__.py
shivyc/tree/decl_nodes.py
shivyc/tree/expr_nodes.py
shivyc/tree/nodes.py
shivyc/tree/utils.py
shivyc-0.5.0.dist-info/DESCRIPTION.rst
shivyc-0.5.0.dist-info/METADATA
shivyc-0.5.0.dist-info/RECORD
shivyc-0.5.0.dist-info/WHEEL
shivyc-0.5.0.dist-info/entry_points.txt
shivyc-0.5.0.dist-info/metadata.json
shivyc-0.5.0.dist-info/top_level.txt
