Metadata-Version: 2.0
Name: shivyc
Version: 0.5.0
Summary: A C compiler written in Python
Home-page: https://github.com/ShivamSarodia/ShivyC
Author: Shivam Sarodia
Author-email: ssarodia@gmail.com
License: MIT
Download-URL: https://github.com/ShivamSarodia/ShivyC/archive/0.5.0.tar.gz
Keywords: shivyc compiler c programming parsing
Platform: UNKNOWN
Classifier: Development Status :: 3 - Alpha
Classifier: Environment :: Console
Classifier: License :: OSI Approved :: MIT License
Classifier: Programming Language :: Python :: 3
Classifier: Programming Language :: Python :: 3.5
Classifier: Programming Language :: Python :: 3.6
Classifier: Programming Language :: C
Classifier: Topic :: Software Development
Classifier: Topic :: Software Development :: Compilers
Classifier: Topic :: Software Development :: Code Generators
Classifier: Topic :: Software Development :: Build Tools
Classifier: Intended Audience :: Developers
Classifier: Intended Audience :: Education
